{
  "orders": [
    {
      "action": "buy",
      "client_order_id": "ac9b21e0-d4b4-47d4-ab2b-d59e224bdbb6",
      "created_time": "2026-02-07T15:48:23.033531Z",
      "expiration_time": null,
      "fill_count": 0,
      "fill_count_fp": "0.00",
      "initial_count": 1,
      "initial_count_fp": "1.00",
      "last_update_time": "2026-02-07T15:48:23.033531Z",
      "maker_fees": 0,
      "maker_fill_cost": 0,
      "maker_fill_cost_dollars": "",
      "no_price": 62,
      "no_price_dollars": "0.6200",
      "order_group_id": null,
      "order_id": "538924b4-d232-4d16-9884-f98016b39836",
      "queue_position": 0,
      "remaining_count": 1,
      "remaining_count_fp": "1.00",
      "side": "yes",
      "status": "resting",
      "subaccount_number": 0,
      "taker_fees": 0,
      "taker_fill_cost": 0,
      "taker_fill_cost_dollars": "",
      "ticker": "KXNCAAMBGAME-26FEB07ASUCOLO-ASU",
      "type": "limit",
      "user_id": "fd194b62-2ac4-452b-8d69-74f98a80cea6",
      "yes_price": 38,
      "yes_price_dollars": "0.3800"
    },
    {
      "action": "buy",
      "client_order_id": "a654d74f-6df2-4e7e-951c-4767a21f1563",
      "created_time": "2026-02-07T15:27:25.303338Z",
      "expiration_time": null,
      "fill_count": 0,
      "fill_count_fp": "0.00",
      "initial_count": 2,
      "initial_count_fp": "2.00",
      "last_update_time": "2026-02-07T15:27:25.303338Z",
      "maker_fees": 0,
      "maker_fill_cost": 0,
      "maker_fill_cost_dollars": "",
      "no_price": 6,
      "no_price_dollars": "0.0600",
      "order_group_id": null,
      "order_id": "2e9eae3a-312e-42f7-a17a-e046a8f91e5f",
      "queue_position": 0,
      "remaining_count": 2,
      "remaining_count_fp": "2.00",
      "side": "no",
      "status": "resting",
      "subaccount_number": 0,
      "taker_fees": 0,
      "taker_fill_cost": 0,
      "taker_fill_cost_dollars": "",
      "ticker": "KXNCAAMBGAME-26FEB07BAYISU-ISU",
      "type": "limit",
      "user_id": "fd194b62-2ac4-452b-8d69-74f98a80cea6",
      "yes_price": 94,
      "yes_price_dollars": "0.9400"
    },
    {
      "action": "buy",
      "client_order_id": "26ace9c8-0ee3-4a9f-926e-cec38644613d",
      "created_time": "2026-02-07T16:30:30.295118Z",
      "expiration_time": null,
      "fill_count": 0,
      "fill_count_fp": "0.00",
      "initial_count": 1,
      "initial_count_fp": "1.00",
      "last_update_time": "2026-02-07T16:30:30.295118Z",
      "maker_fees": 0,
      "maker_fill_cost": 0,
      "maker_fill_cost_dollars": "",
      "no_price": 42,
      "no_price_dollars": "0.4200",
      "order_group_id": null,
      "order_id": "1bb62e87-ec7a-4176-a26b-c4b773aeda92",
      "queue_position": 0,
      "remaining_count": 1,
      "remaining_count_fp": "1.00",
      "side": "no",
      "status": "resting",
      "subaccount_number": 0,
      "taker_fees": 0,
      "taker_fill_cost": 0,
      "taker_fill_cost_dollars": "",
      "ticker": "KXNCAAMBGAME-26FEB07BGSUARST-ARST",
      "type": "limit",
      "user_id": "fd194b62-2ac4-452b-8d69-74f98a80cea6",
      "yes_price": 58,
      "yes_price_dollars": "0.5800"
    },
    {
      "action": "buy",
      "client_order_id": "e7df8b2f-cbf1-4a1c-8e0d-2ff1f58e57d5",
      "created_time": "2026-02-07T15:27:25.155188Z",
      "expiration_time": null,
      "fill_count": 0,
      "fill_count_fp": "0.00",
      "initial_count": 3,
      "initial_count_fp": "3.00",
      "last_update_time": "2026-02-07T15:27:25.155188Z",
      "maker_fees": 0,
      "maker_fill_cost": 0,
      "maker_fill_cost_dollars": "",
      "no_price": 28,
      "no_price_dollars": "0.2800",
      "order_group_id": null,
      "order_id": "513e65f5-65cc-41ad-a2a1-2e1319ba0a59",
      "queue_position": 0,
      "remaining_count": 3,
      "remaining_count_fp": "3.00",
      "side": "no",
      "status": "resting",
      "subaccount_number": 0,
      "taker_fees": 0,
      "taker_fill_cost": 0,
      "taker_fill_cost_dollars": "",
      "ticker": "KXNCAAMBGAME-26FEB07CHSNHC-NHC",
      "type": "limit",
      "user_id": "fd194b62-2ac4-452b-8d69-74f98a80cea6",
      "yes_price": 72,
      "yes_price_dollars": "0.7200"
    },
    {
      "action": "buy",
      "client_order_id": "57056a08-d2ae-4432-b3ae-b5c17c25b304",
      "created_time": "2026-02-07T15:48:22.736149Z",
      "expiration_time": null,
      "fill_count": 0,
      "fill_count_fp": "0.00",
      "initial_count": 1,
      "initial_count_fp": "1.00",
      "last_update_time": "2026-02-07T15:48:22.736149Z",
      "maker_fees": 0,
      "maker_fill_cost": 0,
      "maker_fill_cost_dollars": "",
      "no_price": 44,
      "no_price_dollars": "0.4400",
      "order_group_id": null,
      "order_id": "ed4ab294-70da-433d-90ed-e0e472438533",
      "queue_position": 0,
      "remaining_count": 1,
      "remaining_count_fp": "1.00",
      "side": "no",
      "status": "resting",
      "subaccount_number": 0,
      "taker_fees": 0,
      "taker_fill_cost": 0,
      "taker_fill_cost_dollars": "",
      "ticker": "KXNCAAMBGAME-26FEB07CORCLMB-CLMB",
      "type": "limit",
      "user_id": "fd194b62-2ac4-452b-8d69-74f98a80cea6",
      "yes_price": 56,
      "yes_price_dollars": "0.5600"
    },
    {
      "action": "buy",
      "client_order_id": "32f34ba7-46ed-4d55-850e-dcd9418ee150",
      "created_time": "2026-02-07T15:48:22.885378Z",
      "expiration_time": null,
      "fill_count": 0,
      "fill_count_fp": "0.00",
      "initial_count": 1,
      "initial_count_fp": "1.00",
      "last_update_time": "2026-02-07T15:48:22.885378Z",
      "maker_fees": 0,
      "maker_fill_cost": 0,
      "maker_fill_cost_dollars": "",
      "no_price": 60,
      "no_price_dollars": "0.6000",
      "order_group_id": null,
      "order_id": "495d671e-0509-4988-95e9-ca4bf5b7bbae",
      "queue_position": 0,
      "remaining_count": 1,
      "remaining_count_fp": "1.00",
      "side": "no",
      "status": "resting",
      "subaccount_number": 0,
      "taker_fees": 0,
      "taker_fill_cost": 0,
      "taker_fill_cost_dollars": "",
      "ticker": "KXNCAAMBGAME-26FEB07DETGB-DET",
      "type": "limit",
      "user_id": "fd194b62-2ac4-452b-8d69-74f98a80cea6",
      "yes_price": 40,
      "yes_price_dollars": "0.4000"
    },
    {
      "action": "buy",
      "client_order_id": "cbf95ae7-2d05-4736-abe5-f2789e12b9f5",
      "created_time": "2026-02-07T16:28:30.971725Z",
      "expiration_time": null,
      "fill_count": 0,
      "fill_count_fp": "0.00",
      "initial_count": 2,
      "initial_count_fp": "2.00",
      "last_update_time": "2026-02-07T16:28:30.971725Z",
      "maker_fees": 0,
      "maker_fill_cost": 0,
      "maker_fill_cost_dollars": "",
      "no_price": 34,
      "no_price_dollars": "0.3400",
      "order_group_id": null,
      "order_id": "2b4d43d8-5c38-4499-9644-c99c7ce8211e",
      "queue_position": 0,
      "remaining_count": 2,
      "remaining_count_fp": "2.00",
      "side": "no",
      "status": "resting",
      "subaccount_number": 0,
      "taker_fees": 0,
      "taker_fill_cost": 0,
      "taker_fill_cost_dollars": "",
      "ticker": "KXNCAAMBGAME-26FEB07DREXELON-ELON",
      "type": "limit",
      "user_id": "fd194b62-2ac4-452b-8d69-74f98a80cea6",
      "yes_price": 66,
      "yes_price_dollars": "0.6600"
    },
    {
      "action": "buy",
      "client_order_id": "21953ae2-a53e-49c4-b2d6-6dff8237d5b7",
      "created_time": "2026-02-07T15:58:55.351875Z",
      "expiration_time": null,
      "fill_count": 0,
      "fill_count_fp": "0.00",
      "initial_count": 1,
      "initial_count_fp": "1.00",
      "last_update_time": "2026-02-07T15:58:55.351875Z",
      "maker_fees": 0,
      "maker_fill_cost": 0,
      "maker_fill_cost_dollars": "",
      "no_price": 53,
      "no_price_dollars": "0.5300",
      "order_group_id": null,
      "order_id": "c0aaa2dd-9815-4a54-a7ab-264573531f51",
      "queue_position": 0,
      "remaining_count": 1,
      "remaining_count_fp": "1.00",
      "side": "yes",
      "status": "resting",
      "subaccount_number": 0,
      "taker_fees": 0,
      "taker_fill_cost": 0,
      "taker_fill_cost_dollars": "",
      "ticker": "KXNCAAMBGAME-26FEB07FGCUBELL-BELL",
      "type": "limit",
      "user_id": "fd194b62-2ac4-452b-8d69-74f98a80cea6",
      "yes_price": 47,
      "yes_price_dollars": "0.4700"
    },
    {
      "action": "buy",
      "client_order_id": "8e1c13e2-7e9d-44f9-9041-e1fd6cc31432",
      "created_time": "2026-02-07T15:27:25.748881Z",
      "expiration_time": null,
      "fill_count": 0,
      "fill_count_fp": "0.00",
      "initial_count": 2,
      "initial_count_fp": "2.00",
      "last_update_time": "2026-02-07T15:27:25.748881Z",
      "maker_fees": 0,
      "maker_fill_cost": 0,
      "maker_fill_cost_dollars": "",
      "no_price": 24,
      "no_price_dollars": "0.2400",
      "order_group_id": null,
      "order_id": "f940ff7e-85ad-40cf-979f-cb4d868c93ef",
      "queue_position": 0,
      "remaining_count": 2,
      "remaining_count_fp": "2.00",
      "side": "no",
      "status": "resting",
      "subaccount_number": 0,
      "taker_fees": 0,
      "taker_fill_cost": 0,
      "taker_fill_cost_dollars": "",
      "ticker": "KXNCAAMBGAME-26FEB07JOESGMU-GMU",
      "type": "limit",
      "user_id": "fd194b62-2ac4-452b-8d69-74f98a80cea6",
      "yes_price": 76,
      "yes_price_dollars": "0.7600"
    },
    {
      "action": "buy",
      "client_order_id": "1021a828-8cea-4a5e-b773-762fcfc98021",
      "created_time": "2026-02-07T15:40:30.390564Z",
      "expiration_time": null,
      "fill_count": 0,
      "fill_count_fp": "0.00",
      "initial_count": 3,
      "initial_count_fp": "3.00",
      "last_update_time": "2026-02-07T15:40:30.390564Z",
      "maker_fees": 0,
      "maker_fill_cost": 0,
      "maker_fill_cost_dollars": "",
      "no_price": 80,
      "no_price_dollars": "0.8000",
      "order_group_id": null,
      "order_id": "24a4732c-7a28-4d49-a003-82cfee2730d2",
      "queue_position": 0,
      "remaining_count": 3,
      "remaining_count_fp": "3.00",
      "side": "yes",
      "status": "resting",
      "subaccount_number": 0,
      "taker_fees": 0,
      "taker_fill_cost": 0,
      "taker_fill_cost_dollars": "",
      "ticker": "KXNCAAMBGAME-26FEB07LAMSFA-LAM",
      "type": "limit",
      "user_id": "fd194b62-2ac4-452b-8d69-74f98a80cea6",
      "yes_price": 20,
      "yes_price_dollars": "0.2000"
    },
    {
      "action": "buy",
      "client_order_id": "fa51a6bc-8d97-4dce-a4a1-a96fa5e6f81f",
      "created_time": "2026-02-07T15:27:26.3421Z",
      "expiration_time": null,
      "fill_count": 0,
      "fill_count_fp": "0.00",
      "initial_count": 1,
      "initial_count_fp": "1.00",
      "last_update_time": "2026-02-07T15:27:26.3421Z",
      "maker_fees": 0,
      "maker_fill_cost": 0,
      "maker_fill_cost_dollars": "",
      "no_price": 53,
      "no_price_dollars": "0.5300",
      "order_group_id": null,
      "order_id": "d16a47b6-1021-4ae1-ac89-17e219971675",
      "queue_position": 0,
      "remaining_count": 1,
      "remaining_count_fp": "1.00",
      "side": "yes",
      "status": "resting",
      "subaccount_number": 0,
      "taker_fees": 0,
      "taker_fill_cost": 0,
      "taker_fill_cost_dollars": "",
      "ticker": "KXNCAAMBGAME-26FEB07MRSTFAIR-FAIR",
      "type": "limit",
      "user_id": "fd194b62-2ac4-452b-8d69-74f98a80cea6",
      "yes_price": 47,
      "yes_price_dollars": "0.4700"
    },
    {
      "action": "buy",
      "client_order_id": "b1da9bc5-f805-4db6-96c2-a90cfa14cb65",
      "created_time": "2026-02-07T15:27:25.601943Z",
      "expiration_time": null,
      "fill_count": 0,
      "fill_count_fp": "0.00",
      "initial_count": 2,
      "initial_count_fp": "2.00",
      "last_update_time": "2026-02-07T15:27:25.601943Z",
      "maker_fees": 0,
      "maker_fill_cost": 0,
      "maker_fill_cost_dollars": "",
      "no_price": 88,
      "no_price_dollars": "0.8800",
      "order_group_id": null,
      "order_id": "dbc82fe7-37e8-4ec4-b8ce-6859a9c93fba",
      "queue_position": 0,
      "remaining_count": 2,
      "remaining_count_fp": "2.00",
      "side": "yes",
      "status": "resting",
      "subaccount_number": 0,
      "taker_fees": 0,
      "taker_fill_cost": 0,
      "taker_fill_cost_dollars": "",
      "ticker": "KXNCAAMBGAME-26FEB07OKLAVAN-OKLA",
      "type": "limit",
      "user_id": "fd194b62-2ac4-452b-8d69-74f98a80cea6",
      "yes_price": 12,
      "yes_price_dollars": "0.1200"
    },
    {
      "action": "buy",
      "client_order_id": "3634f5e1-a10e-4e61-bb2f-16716518d5c5",
      "created_time": "2026-02-07T16:19:58.565098Z",
      "expiration_time": null,
      "fill_count": 0,
      "fill_count_fp": "0.00",
      "initial_count": 2,
      "initial_count_fp": "2.00",
      "last_update_time": "2026-02-07T16:19:58.565098Z",
      "maker_fees": 0,
      "maker_fill_cost": 0,
      "maker_fill_cost_dollars": "",
      "no_price": 97,
      "no_price_dollars": "0.9700",
      "order_group_id": null,
      "order_id": "08bbc26a-4e0a-476b-b74e-de28a3fac12f",
      "queue_position": 0,
      "remaining_count": 2,
      "remaining_count_fp": "2.00",
      "side": "yes",
      "status": "resting",
      "subaccount_number": 0,
      "taker_fees": 0,
      "taker_fill_cost": 0,
      "taker_fill_cost_dollars": "",
      "ticker": "KXNCAAMBGAME-26FEB07OREPUR-ORE",
      "type": "limit",
      "user_id": "fd194b62-2ac4-452b-8d69-74f98a80cea6",
      "yes_price": 3,
      "yes_price_dollars": "0.0300"
    },
    {
      "action": "buy",
      "client_order_id": "3dff4b00-612a-4b06-806a-ae9a96dab665",
      "created_time": "2026-02-07T16:19:58.714259Z",
      "expiration_time": null,
      "fill_count": 0,
      "fill_count_fp": "0.00",
      "initial_count": 1,
      "initial_count_fp": "1.00",
      "last_update_time": "2026-02-07T16:19:58.714259Z",
      "maker_fees": 0,
      "maker_fill_cost": 0,
      "maker_fill_cost_dollars": "",
      "no_price": 62,
      "no_price_dollars": "0.6200",
      "order_group_id": null,
      "order_id": "315349d4-82f6-4216-8c4c-7963613adc56",
      "queue_position": 0,
      "remaining_count": 1,
      "remaining_count_fp": "1.00",
      "side": "yes",
      "status": "resting",
      "subaccount_number": 0,
      "taker_fees": 0,
      "taker_fill_cost": 0,
      "taker_fill_cost_dollars": "",
      "ticker": "KXNCAAMBGAME-26FEB07PRINPENN-PRIN",
      "type": "limit",
      "user_id": "fd194b62-2ac4-452b-8d69-74f98a80cea6",
      "yes_price": 38,
      "yes_price_dollars": "0.3800"
    },
    {
      "action": "buy",
      "client_order_id": "34fe635e-4ae6-41ec-a75c-9abb3084eb02",
      "created_time": "2026-02-07T15:48:23.180457Z",
      "expiration_time": null,
      "fill_count": 0,
      "fill_count_fp": "0.00",
      "initial_count": 1,
      "initial_count_fp": "1.00",
      "last_update_time": "2026-02-07T15:48:23.180457Z",
      "maker_fees": 0,
      "maker_fill_cost": 0,
      "maker_fill_cost_dollars": "",
      "no_price": 68,
      "no_price_dollars": "0.6800",
      "order_group_id": null,
      "order_id": "9e732b0f-1bcb-489e-a455-07778fc128f1",
      "queue_position": 0,
      "remaining_count": 1,
      "remaining_count_fp": "1.00",
      "side": "no",
      "status": "resting",
      "subaccount_number": 0,
      "taker_fees": 0,
      "taker_fill_cost": 0,
      "taker_fill_cost_dollars": "",
      "ticker": "KXNCAAMBGAME-26FEB07RICHURI-RICH",
      "type": "limit",
      "user_id": "fd194b62-2ac4-452b-8d69-74f98a80cea6",
      "yes_price": 32,
      "yes_price_dollars": "0.3200"
    },
    {
      "action": "buy",
      "client_order_id": "fb30fed5-d30c-445c-a4f9-28ee7637a32f",
      "created_time": "2026-02-07T15:27:26.042794Z",
      "expiration_time": null,
      "fill_count": 0,
      "fill_count_fp": "0.00",
      "initial_count": 1,
      "initial_count_fp": "1.00",
      "last_update_time": "2026-02-07T15:27:26.042794Z",
      "maker_fees": 0,
      "maker_fill_cost": 0,
      "maker_fill_cost_dollars": "",
      "no_price": 62,
      "no_price_dollars": "0.6200",
      "order_group_id": null,
      "order_id": "371a409e-a859-434d-ba7f-f13c95af9d05",
      "queue_position": 0,
      "remaining_count": 1,
      "remaining_count_fp": "1.00",
      "side": "yes",
      "status": "resting",
      "subaccount_number": 0,
      "taker_fees": 0,
      "taker_fill_cost": 0,
      "taker_fill_cost_dollars": "",
      "ticker": "KXNCAAMBGAME-26FEB07TEMECU-ECU",
      "type": "limit",
      "user_id": "fd194b62-2ac4-452b-8d69-74f98a80cea6",
      "yes_price": 38,
      "yes_price_dollars": "0.3800"
    },
    {
      "action": "buy",
      "client_order_id": "9446b7c8-a0bb-41f6-96a6-503703d35a88",
      "created_time": "2026-02-07T15:45:06.323869Z",
      "expiration_time": null,
      "fill_count": 0,
      "fill_count_fp": "0.00",
      "initial_count": 1,
      "initial_count_fp": "1.00",
      "last_update_time": "2026-02-07T15:45:06.323869Z",
      "maker_fees": 0,
      "maker_fill_cost": 0,
      "maker_fill_cost_dollars": "",
      "no_price": 50,
      "no_price_dollars": "0.5000",
      "order_group_id": null,
      "order_id": "2e379536-8ce3-4297-98ca-4d0f6c87c15a",
      "queue_position": 0,
      "remaining_count": 1,
      "remaining_count_fp": "1.00",
      "side": "yes",
      "status": "resting",
      "subaccount_number": 0,
      "taker_fees": 0,
      "taker_fill_cost": 0,
      "taker_fill_cost_dollars": "",
      "ticker": "KXNCAAMBGAME-26FEB07UCIUCSB-UCSB",
      "type": "limit",
      "user_id": "fd194b62-2ac4-452b-8d69-74f98a80cea6",
      "yes_price": 50,
      "yes_price_dollars": "0.5000"
    },
    {
      "action": "buy",
      "client_order_id": "f75a5267-8d62-4b73-a6c6-432daac83d1d",
      "created_time": "2026-02-07T16:34:26.553257Z",
      "expiration_time": null,
      "fill_count": 0,
      "fill_count_fp": "0.00",
      "initial_count": 2,
      "initial_count_fp": "2.00",
      "last_update_time": "2026-02-07T16:34:26.553257Z",
      "maker_fees": 0,
      "maker_fill_cost": 0,
      "maker_fill_cost_dollars": "",
      "no_price": 5,
      "no_price_dollars": "0.0500",
      "order_group_id": null,
      "order_id": "96dcbf14-f478-43fc-8f06-88d38e0f2683",
      "queue_position": 0,
      "remaining_count": 2,
      "remaining_count_fp": "2.00",
      "side": "no",
      "status": "resting",
      "subaccount_number": 0,
      "taker_fees": 0,
      "taker_fill_cost": 0,
      "taker_fill_cost_dollars": "",
      "ticker": "KXNCAAMBGAME-26FEB07WEBBPRE-PRE",
      "type": "limit",
      "user_id": "fd194b62-2ac4-452b-8d69-74f98a80cea6",
      "yes_price": 95,
      "yes_price_dollars": "0.9500"
    },
    {
      "action": "buy",
      "client_order_id": "2c333979-1894-4a01-84a8-24745248e993",
      "created_time": "2026-02-07T15:31:22.133534Z",
      "expiration_time": null,
      "fill_count": 0,
      "fill_count_fp": "0.00",
      "initial_count": 2,
      "initial_count_fp": "2.00",
      "last_update_time": "2026-02-07T15:31:22.133534Z",
      "maker_fees": 0,
      "maker_fill_cost": 0,
      "maker_fill_cost_dollars": "",
      "no_price": 94,
      "no_price_dollars": "0.9400",
      "order_group_id": null,
      "order_id": "7376bdc2-af41-479c-a4fc-772c153c8f86",
      "queue_position": 0,
      "remaining_count": 2,
      "remaining_count_fp": "2.00",
      "side": "yes",
      "status": "resting",
      "subaccount_number": 0,
      "taker_fees": 0,
      "taker_fill_cost": 0,
      "taker_fill_cost_dollars": "",
      "ticker": "KXNCAAMBGAME-26FEB07WIUTNST-WIU",
      "type": "limit",
      "user_id": "fd194b62-2ac4-452b-8d69-74f98a80cea6",
      "yes_price": 6,
      "yes_price_dollars": "0.0600"
    },
    {
      "action": "buy",
      "client_order_id": "63a9c51d-a60b-40b1-96f1-f40c683658c9",
      "created_time": "2026-02-07T15:27:23.658939Z",
      "expiration_time": null,
      "fill_count": 0,
      "fill_count_fp": "0.00",
      "initial_count": 2,
      "initial_count_fp": "2.00",
      "last_update_time": "2026-02-07T15:27:23.658939Z",
      "maker_fees": 0,
      "maker_fill_cost": 0,
      "maker_fill_cost_dollars": "",
      "no_price": 54,
      "no_price_dollars": "0.5400",
      "order_group_id": null,
      "order_id": "e8f9163b-63e4-40b7-a253-e359ab0ec4b7",
      "queue_position": 0,
      "remaining_count": 2,
      "remaining_count_fp": "2.00",
      "side": "yes",
      "status": "resting",
      "subaccount_number": 0,
      "taker_fees": 0,
      "taker_fill_cost": 0,
      "taker_fill_cost_dollars": "",
      "ticker": "KXNCAAMBTOTAL-26FEB07ALAAUB-176",
      "type": "limit",
      "user_id": "fd194b62-2ac4-452b-8d69-74f98a80cea6",
      "yes_price": 46,
      "yes_price_dollars": "0.4600"
    },
    {
      "action": "buy",
      "client_order_id": "fdd1051e-a24f-4899-b3e4-f4933fea14fc",
      "created_time": "2026-02-07T15:27:23.214106Z",
      "expiration_time": null,
      "fill_count": 0,
      "fill_count_fp": "0.00",
      "initial_count": 3,
      "initial_count_fp": "3.00",
      "last_update_time": "2026-02-07T15:27:23.214106Z",
      "maker_fees": 0,
      "maker_fill_cost": 0,
      "maker_fill_cost_dollars": "",
      "no_price": 55,
      "no_price_dollars": "0.5500",
      "order_group_id": null,
      "order_id": "16953508-5533-44a6-bd1b-cd82f1b2d829",
      "queue_position": 0,
      "remaining_count": 3,
      "remaining_count_fp": "3.00",
      "side": "yes",
      "status": "resting",
      "subaccount_number": 0,
      "taker_fees": 0,
      "taker_fill_cost": 0,
      "taker_fill_cost_dollars": "",
      "ticker": "KXNCAAMBTOTAL-26FEB07BSUUNM-153",
      "type": "limit",
      "user_id": "fd194b62-2ac4-452b-8d69-74f98a80cea6",
      "yes_price": 45,
      "yes_price_dollars": "0.4500"
    },
    {
      "action": "buy",
      "client_order_id": "ee19e045-fd76-4d11-aaf4-ff7cb70fe700",
      "created_time": "2026-02-07T15:27:23.957089Z",
      "expiration_time": null,
      "fill_count": 0,
      "fill_count_fp": "0.00",
      "initial_count": 2,
      "initial_count_fp": "2.00",
      "last_update_time": "2026-02-07T15:27:23.957089Z",
      "maker_fees": 0,
      "maker_fill_cost": 0,
      "maker_fill_cost_dollars": "",
      "no_price": 52,
      "no_price_dollars": "0.5200",
      "order_group_id": null,
      "order_id": "db60a927-3bc3-4723-92a0-e07180089664",
      "queue_position": 0,
      "remaining_count": 2,
      "remaining_count_fp": "2.00",
      "side": "yes",
      "status": "resting",
      "subaccount_number": 0,
      "taker_fees": 0,
      "taker_fill_cost": 0,
      "taker_fill_cost_dollars": "",
      "ticker": "KXNCAAMBTOTAL-26FEB07BUTMARQ-156",
      "type": "limit",
      "user_id": "fd194b62-2ac4-452b-8d69-74f98a80cea6",
      "yes_price": 48,
      "yes_price_dollars": "0.4800"
    },
    {
      "action": "buy",
      "client_order_id": "72a4a9a6-f88e-4d35-a062-75384fc4f108",
      "created_time": "2026-02-07T16:04:10.946839Z",
      "expiration_time": null,
      "fill_count": 0,
      "fill_count_fp": "0.00",
      "initial_count": 1,
      "initial_count_fp": "1.00",
      "last_update_time": "2026-02-07T16:04:10.946839Z",
      "maker_fees": 0,
      "maker_fill_cost": 0,
      "maker_fill_cost_dollars": "",
      "no_price": 53,
      "no_price_dollars": "0.5300",
      "order_group_id": null,
      "order_id": "6ffd5e4c-7e48-43fd-86a8-ffb1cb171816",
      "queue_position": 0,
      "remaining_count": 1,
      "remaining_count_fp": "1.00",
      "side": "yes",
      "status": "resting",
      "subaccount_number": 0,
      "taker_fees": 0,
      "taker_fill_cost": 0,
      "taker_fill_cost_dollars": "",
      "ticker": "KXNCAAMBTOTAL-26FEB07DENUND-161",
      "type": "limit",
      "user_id": "fd194b62-2ac4-452b-8d69-74f98a80cea6",
      "yes_price": 47,
      "yes_price_dollars": "0.4700"
    },
    {
      "action": "buy",
      "client_order_id": "31842c17-261a-48ab-b8f5-b4eee5fd46fa",
      "created_time": "2026-02-07T15:27:23.066677Z",
      "expiration_time": null,
      "fill_count": 0,
      "fill_count_fp": "0.00",
      "initial_count": 4,
      "initial_count_fp": "4.00",
      "last_update_time": "2026-02-07T15:27:23.066677Z",
      "maker_fees": 0,
      "maker_fill_cost": 0,
      "maker_fill_cost_dollars": "",
      "no_price": 57,
      "no_price_dollars": "0.5700",
      "order_group_id": null,
      "order_id": "af25e618-ff05-4dde-b31f-3402e2b5dbf6",
      "queue_position": 0,
      "remaining_count": 4,
      "remaining_count_fp": "4.00",
      "side": "yes",
      "status": "resting",
      "subaccount_number": 0,
      "taker_fees": 0,
      "taker_fill_cost": 0,
      "taker_fill_cost_dollars": "",
      "ticker": "KXNCAAMBTOTAL-26FEB07DUKEUNC-153",
      "type": "limit",
      "user_id": "fd194b62-2ac4-452b-8d69-74f98a80cea6",
      "yes_price": 43,
      "yes_price_dollars": "0.4300"
    },
    {
      "action": "buy",
      "client_order_id": "89a589c1-cac2-4778-846a-12c0d3834e09",
      "created_time": "2026-02-07T16:21:56.751388Z",
      "expiration_time": null,
      "fill_count": 0,
      "fill_count_fp": "0.00",
      "initial_count": 3,
      "initial_count_fp": "3.00",
      "last_update_time": "2026-02-07T16:21:56.751388Z",
      "maker_fees": 0,
      "maker_fill_cost": 0,
      "maker_fill_cost_dollars": "",
      "no_price": 55,
      "no_price_dollars": "0.5500",
      "order_group_id": null,
      "order_id": "827ee87e-fb83-40de-a24c-e26a91d9a8b2",
      "queue_position": 0,
      "remaining_count": 3,
      "remaining_count_fp": "3.00",
      "side": "yes",
      "status": "resting",
      "subaccount_number": 0,
      "taker_fees": 0,
      "taker_fill_cost": 0,
      "taker_fill_cost_dollars": "",
      "ticker": "KXNCAAMBTOTAL-26FEB07GWDUQ-159",
      "type": "limit",
      "user_id": "fd194b62-2ac4-452b-8d69-74f98a80cea6",
      "yes_price": 45,
      "yes_price_dollars": "0.4500"
    },
    {
      "action": "buy",
      "client_order_id": "43a1d1a3-0216-4eb6-bc3a-817e3d29d993",
      "created_time": "2026-02-07T16:35:06.094391Z",
      "expiration_time": null,
      "fill_count": 0,
      "fill_count_fp": "0.00",
      "initial_count": 1,
      "initial_count_fp": "1.00",
      "last_update_time": "2026-02-07T16:35:06.094391Z",
      "maker_fees": 0,
      "maker_fill_cost": 0,
      "maker_fill_cost_dollars": "",
      "no_price": 52,
      "no_price_dollars": "0.5200",
      "order_group_id": null,
      "order_id": "a215c9e2-7465-4015-b5cb-fc3c1171c1b7",
      "queue_position": 0,
      "remaining_count": 1,
      "remaining_count_fp": "1.00",
      "side": "yes",
      "status": "resting",
      "subaccount_number": 0,
      "taker_fees": 0,
      "taker_fill_cost": 0,
      "taker_fill_cost_dollars": "",
      "ticker": "KXNCAAMBTOTAL-26FEB07KSUTCU-154",
      "type": "limit",
      "user_id": "fd194b62-2ac4-452b-8d69-74f98a80cea6",
      "yes_price": 48,
      "yes_price_dollars": "0.4800"
    },
    {
      "action": "buy",
      "client_order_id": "6f97ce3a-e92b-4888-aab8-1328e8571765",
      "created_time": "2026-02-07T15:27:23.509381Z",
      "expiration_time": null,
      "fill_count": 0,
      "fill_count_fp": "0.00",
      "initial_count": 3,
      "initial_count_fp": "3.00",
      "last_update_time": "2026-02-07T15:27:23.509381Z",
      "maker_fees": 0,
      "maker_fill_cost": 0,
      "maker_fill_cost_dollars": "",
      "no_price": 54,
      "no_price_dollars": "0.5400",
      "order_group_id": null,
      "order_id": "86c4b3c0-06b2-47eb-bfe0-f48f8943f2b4",
      "queue_position": 0,
      "remaining_count": 3,
      "remaining_count_fp": "3.00",
      "side": "yes",
      "status": "resting",
      "subaccount_number": 0,
      "taker_fees": 0,
      "taker_fill_cost": 0,
      "taker_fill_cost_dollars": "",
      "ticker": "KXNCAAMBTOTAL-26FEB07MRSTFAIR-138",
      "type": "limit",
      "user_id": "fd194b62-2ac4-452b-8d69-74f98a80cea6",
      "yes_price": 46,
      "yes_price_dollars": "0.4600"
    },
    {
      "action": "buy",
      "client_order_id": "0fe0bf84-897e-4207-bb1c-298a5489008b",
      "created_time": "2026-02-07T16:19:58.416358Z",
      "expiration_time": null,
      "fill_count": 0,
      "fill_count_fp": "0.00",
      "initial_count": 2,
      "initial_count_fp": "2.00",
      "last_update_time": "2026-02-07T16:19:58.416358Z",
      "maker_fees": 0,
      "maker_fill_cost": 0,
      "maker_fill_cost_dollars": "",
      "no_price": 54,
      "no_price_dollars": "0.5400",
      "order_group_id": null,
      "order_id": "8db7132d-b58d-4511-af6c-e43d2a51fe86",
      "queue_position": 0,
      "remaining_count": 2,
      "remaining_count_fp": "2.00",
      "side": "yes",
      "status": "resting",
      "subaccount_number": 0,
      "taker_fees": 0,
      "taker_fill_cost": 0,
      "taker_fill_cost_dollars": "",
      "ticker": "KXNCAAMBTOTAL-26FEB07NEBRUTG-145",
      "type": "limit",
      "user_id": "fd194b62-2ac4-452b-8d69-74f98a80cea6",
      "yes_price": 46,
      "yes_price_dollars": "0.4600"
    },
    {
      "action": "buy",
      "client_order_id": "669a8a10-5142-46fc-a01b-d18c2468db03",
      "created_time": "2026-02-07T15:27:23.80825Z",
      "expiration_time": null,
      "fill_count": 0,
      "fill_count_fp": "0.00",
      "initial_count": 2,
      "initial_count_fp": "2.00",
      "last_update_time": "2026-02-07T15:27:23.80825Z",
      "maker_fees": 0,
      "maker_fill_cost": 0,
      "maker_fill_cost_dollars": "",
      "no_price": 53,
      "no_price_dollars": "0.5300",
      "order_group_id": null,
      "order_id": "6f389223-6ff6-400c-a621-a5cbb48e2897",
      "queue_position": 0,
      "remaining_count": 2,
      "remaining_count_fp": "2.00",
      "side": "yes",
      "status": "resting",
      "subaccount_number": 0,
      "taker_fees": 0,
      "taker_fill_cost": 0,
      "taker_fill_cost_dollars": "",
      "ticker": "KXNCAAMBTOTAL-26FEB07OKSTARIZ-168",
      "type": "limit",
      "user_id": "fd194b62-2ac4-452b-8d69-74f98a80cea6",
      "yes_price": 47,
      "yes_price_dollars": "0.4700"
    },
    {
      "action": "buy",
      "client_order_id": "80612ab4-bd97-47d5-b36d-bc249fa22325",
      "created_time": "2026-02-07T15:27:24.250511Z",
      "expiration_time": null,
      "fill_count": 0,
      "fill_count_fp": "0.00",
      "initial_count": 2,
      "initial_count_fp": "2.00",
      "last_update_time": "2026-02-07T15:27:24.250511Z",
      "maker_fees": 0,
      "maker_fill_cost": 0,
      "maker_fill_cost_dollars": "",
      "no_price": 53,
      "no_price_dollars": "0.5300",
      "order_group_id": null,
      "order_id": "f3abe7da-a341-45f0-8d0f-a7caae79227c",
      "queue_position": 0,
      "remaining_count": 2,
      "remaining_count_fp": "2.00",
      "side": "yes",
      "status": "resting",
      "subaccount_number": 0,
      "taker_fees": 0,
      "taker_fill_cost": 0,
      "taker_fill_cost_dollars": "",
      "ticker": "KXNCAAMBTOTAL-26FEB07OREPUR-144",
      "type": "limit",
      "user_id": "fd194b62-2ac4-452b-8d69-74f98a80cea6",
      "yes_price": 47,
      "yes_price_dollars": "0.4700"
    },
    {
      "action": "buy",
      "client_order_id": "f981b9d0-c431-47a1-a1d3-3c4bc1add452",
      "created_time": "2026-02-07T14:36:25.704906Z",
      "expiration_time": null,
      "fill_count": 0,
      "fill_count_fp": "0.00",
      "initial_count": 2,
      "initial_count_fp": "2.00",
      "last_update_time": "2026-02-07T14:36:25.704906Z",
      "maker_fees": 0,
      "maker_fill_cost": 0,
      "maker_fill_cost_dollars": "",
      "no_price": 53,
      "no_price_dollars": "0.5300",
      "order_group_id": null,
      "order_id": "68b67883-b227-462b-b7d3-61a1c187cc5a",
      "queue_position": 0,
      "remaining_count": 2,
      "remaining_count_fp": "2.00",
      "side": "yes",
      "status": "resting",
      "subaccount_number": 0,
      "taker_fees": 0,
      "taker_fill_cost": 0,
      "taker_fill_cost_dollars": "",
      "ticker": "KXNCAAMBTOTAL-26FEB07SHUMAN-163",
      "type": "limit",
      "user_id": "fd194b62-2ac4-452b-8d69-74f98a80cea6",
      "yes_price": 47,
      "yes_price_dollars": "0.4700"
    },
    {
      "action": "buy",
      "client_order_id": "4394460c-460a-4487-b893-efebfd161d83",
      "created_time": "2026-02-07T15:27:24.713328Z",
      "expiration_time": null,
      "fill_count": 0,
      "fill_count_fp": "0.00",
      "initial_count": 1,
      "initial_count_fp": "1.00",
      "last_update_time": "2026-02-07T15:27:24.713328Z",
      "maker_fees": 0,
      "maker_fill_cost": 0,
      "maker_fill_cost_dollars": "",
      "no_price": 53,
      "no_price_dollars": "0.5300",
      "order_group_id": null,
      "order_id": "1a65bc18-d370-4b37-aeba-7455555eb601",
      "queue_position": 0,
      "remaining_count": 1,
      "remaining_count_fp": "1.00",
      "side": "yes",
      "status": "resting",
      "subaccount_number": 0,
      "taker_fees": 0,
      "taker_fill_cost": 0,
      "taker_fill_cost_dollars": "",
      "ticker": "KXNCAAMBTOTAL-26FEB07STETEKY-151",
      "type": "limit",
      "user_id": "fd194b62-2ac4-452b-8d69-74f98a80cea6",
      "yes_price": 47,
      "yes_price_dollars": "0.4700"
    },
    {
      "action": "buy",
      "client_order_id": "626ae068-6a53-4d4c-988a-255f9a0d589c",
      "created_time": "2026-02-07T15:27:24.103637Z",
      "expiration_time": null,
      "fill_count": 0,
      "fill_count_fp": "0.00",
      "initial_count": 2,
      "initial_count_fp": "2.00",
      "last_update_time": "2026-02-07T15:27:24.103637Z",
      "maker_fees": 0,
      "maker_fill_cost": 0,
      "maker_fill_cost_dollars": "",
      "no_price": 52,
      "no_price_dollars": "0.5200",
      "order_group_id": null,
      "order_id": "de71e6de-9dac-4745-a5c7-1f43d86392d1",
      "queue_position": 0,
      "remaining_count": 2,
      "remaining_count_fp": "2.00",
      "side": "yes",
      "status": "resting",
      "subaccount_number": 0,
      "taker_fees": 0,
      "taker_fill_cost": 0,
      "taker_fill_cost_dollars": "",
      "ticker": "KXNCAAMBTOTAL-26FEB07TENNUK-147",
      "type": "limit",
      "user_id": "fd194b62-2ac4-452b-8d69-74f98a80cea6",
      "yes_price": 48,
      "yes_price_dollars": "0.4800"
    },
    {
      "action": "buy",
      "client_order_id": "f8532081-1bfb-4429-aecf-7f0e9d2b3868",
      "created_time": "2026-02-07T16:28:30.823919Z",
      "expiration_time": null,
      "fill_count": 0,
      "fill_count_fp": "0.00",
      "initial_count": 3,
      "initial_count_fp": "3.00",
      "last_update_time": "2026-02-07T16:28:30.823919Z",
      "maker_fees": 0,
      "maker_fill_cost": 0,
      "maker_fill_cost_dollars": "",
      "no_price": 55,
      "no_price_dollars": "0.5500",
      "order_group_id": null,
      "order_id": "8af05b1b-bd3a-47a8-983a-d92aa9243e71",
      "queue_position": 0,
      "remaining_count": 3,
      "remaining_count_fp": "3.00",
      "side": "yes",
      "status": "resting",
      "subaccount_number": 0,
      "taker_fees": 0,
      "taker_fill_cost": 0,
      "taker_fill_cost_dollars": "",
      "ticker": "KXNCAAMBTOTAL-26FEB07WEBBPRE-146",
      "type": "limit",
      "user_id": "fd194b62-2ac4-452b-8d69-74f98a80cea6",
      "yes_price": 45,
      "yes_price_dollars": "0.4500"
    },
    {
      "action": "buy",
      "client_order_id": "6e3d07c6-d3e3-4122-ba98-753fc2f3bbca",
      "created_time": "2026-02-07T14:33:16.408671Z",
      "expiration_time": null,
      "fill_count": 0,
      "fill_count_fp": "0.00",
      "initial_count": 2,
      "initial_count_fp": "2.00",
      "last_update_time": "2026-02-07T14:33:16.408671Z",
      "maker_fees": 0,
      "maker_fill_cost": 0,
      "maker_fill_cost_dollars": "",
      "no_price": 54,
      "no_price_dollars": "0.5400",
      "order_group_id": null,
      "order_id": "e7e247f8-76d3-4db3-a42a-5bdfe984ea58",
      "queue_position": 0,
      "remaining_count": 2,
      "remaining_count_fp": "2.00",
      "side": "yes",
      "status": "resting",
      "subaccount_number": 0,
      "taker_fees": 0,
      "taker_fill_cost": 0,
      "taker_fill_cost_dollars": "",
      "ticker": "KXNCAAMBTOTAL-26FEB08UCSDHAW-146",
      "type": "limit",
      "user_id": "fd194b62-2ac4-452b-8d69-74f98a80cea6",
      "yes_price": 46,
      "yes_price_dollars": "0.4600"
    },
    {
      "action": "buy",
      "client_order_id": "8ad6aab5-09ad-47d0-b9ce-c1cef6eca1b4",
      "created_time": "2026-02-07T16:09:27.049045Z",
      "expiration_time": null,
      "fill_count": 0,
      "fill_count_fp": "0.00",
      "initial_count": 2,
      "initial_count_fp": "2.00",
      "last_update_time": "2026-02-07T16:09:27.049045Z",
      "maker_fees": 0,
      "maker_fill_cost": 0,
      "maker_fill_cost_dollars": "",
      "no_price": 3,
      "no_price_dollars": "0.0300",
      "order_group_id": null,
      "order_id": "27343a44-a107-4cb8-9ddb-949596dc2158",
      "queue_position": 0,
      "remaining_count": 2,
      "remaining_count_fp": "2.00",
      "side": "no",
      "status": "resting",
      "subaccount_number": 0,
      "taker_fees": 0,
      "taker_fill_cost": 0,
      "taker_fill_cost_dollars": "",
      "ticker": "KXNCAAWBGAME-26FEB07ARIZWVU-WVU",
      "type": "limit",
      "user_id": "fd194b62-2ac4-452b-8d69-74f98a80cea6",
      "yes_price": 97,
      "yes_price_dollars": "0.9700"
    },
    {
      "action": "buy",
      "client_order_id": "75732a25-ea99-4f59-892e-e2dec327c4c9",
      "created_time": "2026-02-07T15:58:54.759507Z",
      "expiration_time": null,
      "fill_count": 0,
      "fill_count_fp": "0.00",
      "initial_count": 6,
      "initial_count_fp": "6.00",
      "last_update_time": "2026-02-07T15:58:54.759507Z",
      "maker_fees": 0,
      "maker_fill_cost": 0,
      "maker_fill_cost_dollars": "",
      "no_price": 12,
      "no_price_dollars": "0.1200",
      "order_group_id": null,
      "order_id": "d9f8534d-68a3-45e3-b3d0-575e7211c6db",
      "queue_position": 0,
      "remaining_count": 6,
      "remaining_count_fp": "6.00",
      "side": "no",
      "status": "resting",
      "subaccount_number": 0,
      "taker_fees": 0,
      "taker_fill_cost": 0,
      "taker_fill_cost_dollars": "",
      "ticker": "KXNCAAWBGAME-26FEB07ASUBAY-BAY",
      "type": "limit",
      "user_id": "fd194b62-2ac4-452b-8d69-74f98a80cea6",
      "yes_price": 88,
      "yes_price_dollars": "0.8800"
    },
    {
      "action": "buy",
      "client_order_id": "8b7f55b5-0224-438e-aedf-3faa3743c641",
      "created_time": "2026-02-07T15:58:55.056633Z",
      "expiration_time": null,
      "fill_count": 0,
      "fill_count_fp": "0.00",
      "initial_count": 2,
      "initial_count_fp": "2.00",
      "last_update_time": "2026-02-07T15:58:55.056633Z",
      "maker_fees": 0,
      "maker_fill_cost": 0,
      "maker_fill_cost_dollars": "",
      "no_price": 50,
      "no_price_dollars": "0.5000",
      "order_group_id": null,
      "order_id": "f8214d21-2b43-48bc-96f8-8e4b144dcfc6",
      "queue_position": 0,
      "remaining_count": 2,
      "remaining_count_fp": "2.00",
      "side": "yes",
      "status": "resting",
      "subaccount_number": 0,
      "taker_fees": 0,
      "taker_fill_cost": 0,
      "taker_fill_cost_dollars": "",
      "ticker": "KXNCAAWBGAME-26FEB07MDNEB-MD",
      "type": "limit",
      "user_id": "fd194b62-2ac4-452b-8d69-74f98a80cea6",
      "yes_price": 50,
      "yes_price_dollars": "0.5000"
    },
    {
      "action": "buy",
      "client_order_id": "22d96ad8-ad0a-4709-bba8-83b311a12877",
      "created_time": "2026-02-07T15:58:55.203436Z",
      "expiration_time": null,
      "fill_count": 0,
      "fill_count_fp": "0.00",
      "initial_count": 1,
      "initial_count_fp": "1.00",
      "last_update_time": "2026-02-07T15:58:55.203436Z",
      "maker_fees": 0,
      "maker_fill_cost": 0,
      "maker_fill_cost_dollars": "",
      "no_price": 56,
      "no_price_dollars": "0.5600",
      "order_group_id": null,
      "order_id": "09bf70f9-96c1-4565-b67b-09fe514e4bfa",
      "queue_position": 0,
      "remaining_count": 1,
      "remaining_count_fp": "1.00",
      "side": "yes",
      "status": "resting",
      "subaccount_number": 0,
      "taker_fees": 0,
      "taker_fill_cost": 0,
      "taker_fill_cost_dollars": "",
      "ticker": "KXNCAAWBGAME-26FEB07MDNEB-NEB",
      "type": "limit",
      "user_id": "fd194b62-2ac4-452b-8d69-74f98a80cea6",
      "yes_price": 44,
      "yes_price_dollars": "0.4400"
    },
    {
      "action": "buy",
      "client_order_id": "b8dd2ded-c643-4703-99ac-a88d1ebd2ae4",
      "created_time": "2026-02-07T15:58:54.908795Z",
      "expiration_time": null,
      "fill_count": 0,
      "fill_count_fp": "0.00",
      "initial_count": 2,
      "initial_count_fp": "2.00",
      "last_update_time": "2026-02-07T15:58:54.908795Z",
      "maker_fees": 0,
      "maker_fill_cost": 0,
      "maker_fill_cost_dollars": "",
      "no_price": 3,
      "no_price_dollars": "0.0300",
      "order_group_id": null,
      "order_id": "d9eb0903-b7be-4159-a61b-912cc8d6672b",
      "queue_position": 0,
      "remaining_count": 2,
      "remaining_count_fp": "2.00",
      "side": "no",
      "status": "resting",
      "subaccount_number": 0,
      "taker_fees": 0,
      "taker_fill_cost": 0,
      "taker_fill_cost_dollars": "",
      "ticker": "KXNCAAWBGAME-26FEB07TTUHOU-TTU",
      "type": "limit",
      "user_id": "fd194b62-2ac4-452b-8d69-74f98a80cea6",
      "yes_price": 97,
      "yes_price_dollars": "0.9700"
    }
  ]
}